scatter3d/__init__.py
scatter3d/scatter3d.py
scatter3d/static/scatter3d.js
scatter3d/static/scatter3d.js.map
scatter3d/widget_test.py
scatter3d_anywidget-0.1.7.dist-info/WHEEL
scatter3d_anywidget-0.1.7.dist-info/METADATA
scatter3d_anywidget-0.1.7.dist-info/RECORD
