Metadata-Version: 2.3
Name: scatter3d-anywidget
Version: 0.1.7
Summary: 3D scatter widget with lasso selection
License: MIT
Classifier: Development Status :: 3 - Alpha
Classifier: License :: OSI Approved :: MIT License
Classifier: Programming Language :: Python :: 3
Classifier: Programming Language :: Python :: 3.13
Classifier: Intended Audience :: Science/Research
Classifier: Topic :: Scientific/Engineering :: Visualization
Requires-Dist: anywidget>=0.9.21
Requires-Dist: narwhals>=2.14.0
Requires-Dist: numpy>=2.3.5
Requires-Python: >=3.13
Project-URL: Homepage, https://github.com/JoseBlanca/any_scatter3d
Project-URL: Repository, https://github.com/JoseBlanca/any_scatter3d
Project-URL: Issues, https://github.com/JoseBlanca/any_scatter3d/issues
